ore/__init__.py
ore/annotations.py
ore/enrich_utils.py
ore/enrichment.py
ore/genes.py
ore/join_dna_rna.py
ore/ore.py
ore/outliers.py
ore/permute_enrichment.py
ore/plotting.py
ore/utils.py
ore/variants.py
ore/vcf.py
ore/vcf_utils.py
ore/version.py
ore/annovar/annotate_variation.pl
ore/annovar/table_annovar.pl
ore/data/gene_strand_hg19.txt.gz
ore/data/gene_strand_hg38.txt.gz
ore/data/hg19_genome_masks/hg19_lcr_hs37d5.bed.gz
ore/data/hg19_genome_masks/hg19_lcr_hs37d5.bed.gz.tbi
ore/data/hg19_genome_masks/hg19_segdup.bed.gz
ore/data/hg19_genome_masks/hg19_segdup.bed.gz.tbi
ore-0.2.1.dist-info/LICENSE.txt
ore-0.2.1.dist-info/METADATA
ore-0.2.1.dist-info/RECORD
ore-0.2.1.dist-info/WHEEL
ore-0.2.1.dist-info/entry_points.txt
ore-0.2.1.dist-info/top_level.txt
