Metadata-Version: 2.1
Name: ore
Version: 0.2.1
Summary: Associate outliers with rare variation
Home-page: http://github.com/frichter/ore
Author: Felix Richter
Author-email: felix.richter@icahn.mssm.edu
License: MIT
Keywords: rnaseq,wgs,outliers,rare_variants,rna,dna
Platform: UNKNOWN
Classifier: Development Status :: 3 - Alpha
Classifier: Intended Audience :: Science/Research
Classifier: License :: OSI Approved :: MIT License
Classifier: Programming Language :: Python :: 3 :: Only
Classifier: Topic :: Scientific/Engineering
Classifier: Topic :: Scientific/Engineering :: Bio-Informatics
Classifier: Topic :: Scientific/Engineering :: Medical Science Apps.
Requires-Python: >=3
Requires-Dist: pandas
Requires-Dist: pybedtools
Requires-Dist: scipy
Requires-Dist: matplotlib
Requires-Dist: numpy
Requires-Dist: statsmodels
Requires-Dist: pysam
